ShujujiegouYuSuanfaTengxunJingxuanLianxi50TiV10Fix1/README.md
ShujujiegouYuSuanfaTengxunJingxuanLianxi50TiV10Fix1/__init__.py
ShujujiegouYuSuanfaTengxunJingxuanLianxi50TiV10Fix1/__main__.py
ShujujiegouYuSuanfaTengxunJingxuanLianxi50TiV10Fix1/file.pdf
ShujujiegouYuSuanfaTengxunJingxuanLianxi50TiV10Fix1/index.html
shujujiegou_yu_suanfa_tengxun_jingxuan_lianxi_50_ti_v1_0_fix1-2025.3.24.1.dist-info/METADATA
shujujiegou_yu_suanfa_tengxun_jingxuan_lianxi_50_ti_v1_0_fix1-2025.3.24.1.dist-info/WHEEL
shujujiegou_yu_suanfa_tengxun_jingxuan_lianxi_50_ti_v1_0_fix1-2025.3.24.1.dist-info/entry_points.txt
shujujiegou_yu_suanfa_tengxun_jingxuan_lianxi_50_ti_v1_0_fix1-2025.3.24.1.dist-info/top_level.txt
shujujiegou_yu_suanfa_tengxun_jingxuan_lianxi_50_ti_v1_0_fix1-2025.3.24.1.dist-info/RECORD
